LICENSE
MANIFEST.in
README.rst
setup.py
doc/Makefile
doc/make.bat
doc/make_doc_images.py
doc/images/coef_table.png
doc/images/lena_dwt.png
doc/source/conf.py
doc/source/index.rst
doc/source/install.rst
doc/source/license.rst
doc/source/reference.rst
doc/source/tutorial.rst
doc/source/wavelets.rst
doc/source/sphinxext/apigen.py
doc/source/sphinxext/docscrape.py
doc/source/sphinxext/docscrape_sphinx.py
doc/source/sphinxext/inheritance_diagram.py
doc/source/sphinxext/ipython_console_highlighting.py
doc/source/sphinxext/numpydoc.py
pyrwt.egg-info/PKG-INFO
pyrwt.egg-info/SOURCES.txt
pyrwt.egg-info/dependency_links.txt
pyrwt.egg-info/top_level.txt
rwt/__init__.py
rwt/utilities.py
rwt/wavelets.py
src/cyrwt.c
src/cyrwt.pyx
src/dwtaxis.c
src/mdwt_r.c
src/midwt_r.c
src/mirdwt_r.c
src/mrdwt_r.c
src/rwt.h
src/rwt.pxd