Metadata-Version: 1.1
Name: pyrwt
Version: 0.2.2
Summary: A cython wrapper for the Rice Wavelet Toolbox
Home-page: http://bitbucket.org/amitibo/pyrwt
Author: Amit Aides
Author-email: amitibo@tx.technion.ac.il
License: BSD
Keywords: wavelets,wavelet transform,DWT
Platform: UNKNOWN
Classifier: License :: OSI Approved :: BSD License
Classifier: Development Status :: 3 - Alpha
Classifier: Topic :: Scientific/Engineering
